dicom_contour/__init__.py
dicom_contour/contour.py
dicom_contour/plots.py
dicom_contour/to_numpy.py
dicom_contour/utils.py
dicom_contour-2.dist-info/DESCRIPTION.rst
dicom_contour-2.dist-info/METADATA
dicom_contour-2.dist-info/RECORD
dicom_contour-2.dist-info/WHEEL
dicom_contour-2.dist-info/metadata.json
dicom_contour-2.dist-info/top_level.txt
