Metadata-Version: 2.0
Name: dicom-contour
Version: 2
Summary: A library which converts DICOM images and contours into numpy arrays. An automated way of extracting image and mask voxels.
Home-page: https://github.com/KeremTurgutlu/dicom-contour
Author: Kerem Turgutlu
Author-email: kcturgutlu@dons.usfca.edu
License: MIT
Keywords: dicom,contour,mask,medical image
Platform: UNKNOWN
Requires-Dist: matplotlib
Requires-Dist: numpy
Requires-Dist: pydicom
